{
  "generado": "2026-02-12T12:40:14.098Z",
  "modo": "live",
  "rutas": [
    {
      "ts": "2026-02-12T12:40:45.713Z",
      "ruta": "LIM-MIA",
      "min": null,
      "max": null,
      "prom": null,
      "ultimo": null,
      "tope": 5300,
      "fuente": "google_flights"
    },
    {
      "ts": "2026-02-12T12:41:16.184Z",
      "ruta": "LIM-FLL",
      "min": null,
      "max": null,
      "prom": null,
      "ultimo": null,
      "tope": 5300,
      "fuente": "google_flights"
    },
    {
      "ts": "2026-02-12T12:41:46.709Z",
      "ruta": "LIM-MCO",
      "min": null,
      "max": null,
      "prom": null,
      "ultimo": null,
      "tope": 5400,
      "fuente": "google_flights"
    }
  ]
}