{
  "generado": "2026-07-18T21:40:18.887Z",
  "modo": "live",
  "rutas": [
    {
      "ts": "2026-07-18T21:40:50.547Z",
      "ruta": "LIM-MIA",
      "min": null,
      "max": null,
      "prom": null,
      "ultimo": null,
      "tope": 5300,
      "fuente": "google_flights"
    },
    {
      "ts": "2026-07-18T21:41:21.193Z",
      "ruta": "LIM-FLL",
      "min": null,
      "max": null,
      "prom": null,
      "ultimo": null,
      "tope": 5300,
      "fuente": "google_flights"
    },
    {
      "ts": "2026-07-18T21:41:51.855Z",
      "ruta": "LIM-MCO",
      "min": null,
      "max": null,
      "prom": null,
      "ultimo": null,
      "tope": 5400,
      "fuente": "google_flights"
    }
  ]
}