{
  "generado": "2026-02-20T01:08:42.731Z",
  "modo": "live",
  "rutas": [
    {
      "ts": "2026-02-20T01:09:13.778Z",
      "ruta": "LIM-MIA",
      "min": null,
      "max": null,
      "prom": null,
      "ultimo": null,
      "tope": 5300,
      "fuente": "google_flights"
    },
    {
      "ts": "2026-02-20T01:09:44.670Z",
      "ruta": "LIM-FLL",
      "min": null,
      "max": null,
      "prom": null,
      "ultimo": null,
      "tope": 5300,
      "fuente": "google_flights"
    },
    {
      "ts": "2026-02-20T01:10:15.340Z",
      "ruta": "LIM-MCO",
      "min": null,
      "max": null,
      "prom": null,
      "ultimo": null,
      "tope": 5400,
      "fuente": "google_flights"
    }
  ]
}