{
  "generado": "2025-12-23T18:18:26.157Z",
  "modo": "live",
  "rutas": [
    {
      "ts": "2025-12-23T18:18:57.482Z",
      "ruta": "LIM-MIA",
      "min": null,
      "max": null,
      "prom": null,
      "ultimo": null,
      "tope": 5300,
      "fuente": "google_flights"
    },
    {
      "ts": "2025-12-23T18:19:28.133Z",
      "ruta": "LIM-FLL",
      "min": null,
      "max": null,
      "prom": null,
      "ultimo": null,
      "tope": 5300,
      "fuente": "google_flights"
    },
    {
      "ts": "2025-12-23T18:19:58.730Z",
      "ruta": "LIM-MCO",
      "min": null,
      "max": null,
      "prom": null,
      "ultimo": null,
      "tope": 5400,
      "fuente": "google_flights"
    }
  ]
}