{
  "generado": "2026-01-24T18:17:46.520Z",
  "modo": "live",
  "rutas": [
    {
      "ts": "2026-01-24T18:18:20.725Z",
      "ruta": "LIM-MIA",
      "min": null,
      "max": null,
      "prom": null,
      "ultimo": null,
      "tope": 5300,
      "fuente": "google_flights"
    },
    {
      "ts": "2026-01-24T18:18:51.471Z",
      "ruta": "LIM-FLL",
      "min": null,
      "max": null,
      "prom": null,
      "ultimo": null,
      "tope": 5300,
      "fuente": "google_flights"
    },
    {
      "ts": "2026-01-24T18:19:22.116Z",
      "ruta": "LIM-MCO",
      "min": null,
      "max": null,
      "prom": null,
      "ultimo": null,
      "tope": 5400,
      "fuente": "google_flights"
    }
  ]
}